[{"_path":"/ai-robotics-100q/part3","_dir":"ai-robotics-100q","_draft":false,"_partial":false,"_locale":"","title":"Part 3: Control and Manipulation (Questions 29-45)","description":"Dive deep into the core algorithms that enable robots to move, interact, and perform complex tasks with precision and intelligence.","icon":"carbon:course","lastModified":"Jul 15, 2025","_type":"markdown","_id":"content:ai-robotics-100q:4.part3.md","_source":"content","_file":"ai-robotics-100q/4.part3.md","_stem":"ai-robotics-100q/4.part3","_extension":"md"},{"_path":"/ai-robotics-100q/part5","_dir":"ai-robotics-100q","_draft":false,"_partial":false,"_locale":"","title":"Part 5: Human-Robot Interaction (HRI) (Questions 64-78)","description":"Explore the complexities of building robots that can safely and intuitively interact with humans, from understanding voice and gestures to modeling emotions and long-term relationships.","icon":"carbon:course","lastModified":"Jul 15, 2025","_type":"markdown","_id":"content:ai-robotics-100q:6.part5.md","_source":"content","_file":"ai-robotics-100q/6.part5.md","_stem":"ai-robotics-100q/6.part5","_extension":"md"}]